edge_mender/__init__.py
edge_mender/data_factory.py
edge_mender/edge_mender.py
edge_mender/geometry_helper.py
edge_mender/mesh_generator.py
edge_mender/visualizer.py
edge_mender-0.1.0.dist-info/licenses/LICENSE
edge_mender-0.1.0.dist-info/METADATA
edge_mender-0.1.0.dist-info/WHEEL
edge_mender-0.1.0.dist-info/top_level.txt
edge_mender-0.1.0.dist-info/RECORD
