Metadata-Version: 2.4
Name: edge-mender
Version: 0.1.0
Summary: A Topology Repair Algorithm for Voxel Boundary Meshes
Author-email: Matthew Vine <mattvine03@gmail.com>
License-Expression: MIT
Keywords: mesh,manifold,topology,voxel,3d,geometry
Requires-Python: >=3.11
License-File: LICENSE
Requires-Dist: numpy>=2.3.4
Requires-Dist: scipy>=1.16.3
Requires-Dist: trimesh>=4.9.0
Provides-Extra: utils
Requires-Dist: connected-components-3d>=3.26.1; extra == "utils"
Requires-Dist: fill-voids>=2.1.1; extra == "utils"
Requires-Dist: itk>=5.4.5; extra == "utils"
Requires-Dist: itk-cuberille>=2.7.2; extra == "utils"
Requires-Dist: manifold3d>=3.3.2; extra == "utils"
Requires-Dist: panda3d>=1.10.15; extra == "utils"
Requires-Dist: pandas>=2.3.3; extra == "utils"
Requires-Dist: pyvista>=0.46.4; extra == "utils"
Provides-Extra: dev
Requires-Dist: edge_mender[utils]; extra == "dev"
Requires-Dist: fast-simplification>=0.1.12; extra == "dev"
Requires-Dist: networkx>=3.6; extra == "dev"
Requires-Dist: pre-commit>=4.5.0; extra == "dev"
Requires-Dist: pytest>=9.0.1; extra == "dev"
Requires-Dist: pytest-cov>=7.0.0; extra == "dev"
Requires-Dist: pytest-mock>=3.15.1; extra == "dev"
Requires-Dist: ruff>=0.14.7; extra == "dev"
Requires-Dist: uv>=0.9.14; extra == "dev"
Provides-Extra: examples
Requires-Dist: edge_mender[utils]; extra == "examples"
Requires-Dist: ipykernel>=7.1.0; extra == "examples"
Requires-Dist: ipywidgets>=8.1.8; extra == "examples"
Requires-Dist: networkx>=3.6; extra == "examples"
Requires-Dist: trame>=3.12.0; extra == "examples"
Requires-Dist: trame-server>=3.8.1; extra == "examples"
Requires-Dist: trame-vtk>=2.10.0; extra == "examples"
Requires-Dist: trame-vuetify>=3.1.0; extra == "examples"
Provides-Extra: eval
Requires-Dist: edge_mender[examples,utils]; extra == "eval"
Requires-Dist: nibabel>=5.3.2; extra == "eval"
Requires-Dist: openpyxl>=3.1.5; extra == "eval"
Requires-Dist: tqdm>=4.67.1; extra == "eval"
Dynamic: license-file
